librair/__init__.py
librair/__main__.py
librair/endpoints.py
librair/parsers.py
librair/interfaces/__init__.py
librair/interfaces/hydra.py
librair/interfaces/sru.py
librair/interfaces/unapi.py
librair/protocols/__init__.py
librair/protocols/http.py
librair/protocols/sru.py
librair/schemas/__init__.py
librair/schemas/json.py
librair/schemas/plain.py
librair/schemas/xml.py
librair/services/__init__.py
librair/services/cerl.py
librair/services/dnb.py
librair/services/entityfacts.py
librair/services/gnd.py
librair/services/kalliope.py
librair/services/lobid.py
librair/services/oclc.py
librair/services/seealso.py
librair/services/viaf.py
librair/services/zdb.py
librair-2022.11.27.dist-info/LICENSE
librair-2022.11.27.dist-info/METADATA
librair-2022.11.27.dist-info/WHEEL
librair-2022.11.27.dist-info/top_level.txt
librair-2022.11.27.dist-info/RECORD
