Metadata-Version: 2.1
Name: librair
Version: 2022.11.27
Summary: retrieve data from library catalogs
Home-page: https://github.com/herreio/librair
Author: Donatus Herre
Author-email: pypi@herre.io
License: MIT
Classifier: Intended Audience :: Science/Research
Classifier: Intended Audience :: Developers
Classifier: Programming Language :: Python :: 3
Classifier: Operating System :: OS Independent
Classifier: License :: OSI Approved :: MIT License
License-File: LICENSE
Requires-Dist: certifi (==2022.9.24)
Requires-Dist: charset-normalizer (==2.1.1)
Requires-Dist: idna (==3.4)
Requires-Dist: lxml (==4.9.1)
Requires-Dist: requests (==2.28.1)
Requires-Dist: tqdm (==4.64.1)
Requires-Dist: urllib3 (==1.26.13)
